dimp/__init__.py
dimp/crypto/__init__.py
dimp/crypto/algorithms.py
dimp/crypto/keys.py
dimp/crypto/pnf.py
dimp/crypto/ted.py
dimp/dkd/__init__.py
dimp/ext/__init__.py
dimp/mkm/__init__.py
dimp/mkm/docs.py
dimp/mkm/document.py
dimp/mkm/meta.py
dimp/msg/__init__.py
dimp/msg/base.py
dimp/msg/envelope.py
dimp/msg/instant.py
dimp/msg/reliable.py
dimp/msg/secure.py
dimp/protocol/__init__.py
dimp/protocol/app.py
dimp/protocol/assets.py
dimp/protocol/base.py
dimp/protocol/commands.py
dimp/protocol/contents.py
dimp/protocol/docs.py
dimp/protocol/files.py
dimp/protocol/forward.py
dimp/protocol/groups.py
dimp/protocol/helpers.py
dimp/protocol/quote.py
dimp/protocol/receipt.py
dimp/protocol/types.py
dimp-2.3.4.dist-info/LICENSE
dimp-2.3.4.dist-info/METADATA
dimp-2.3.4.dist-info/WHEEL
dimp-2.3.4.dist-info/top_level.txt
dimp-2.3.4.dist-info/RECORD
