Metadata-Version: 2.1
Name: dimp
Version: 2.3.4
Summary: Decentralized Instant Messaging Protocol
Home-page: https://github.com/dimchat/core-py
Author: Albert Moky
Author-email: albert.moky@gmail.com
License: MIT
Classifier: Programming Language :: Python :: 3
Classifier: License :: OSI Approved :: MIT License
Classifier: Operating System :: OS Independent
License-File: LICENSE
Requires-Dist: dkd (>=2.3.4)
Requires-Dist: mkm (>=2.3.4)
